zillow_api/__init__.py
zillow_api/__version__.py
zillow_api/client.py
zillow_api/default_headers.py
zillow_api_s-1.0.1.dist-info/LICENSE
zillow_api_s-1.0.1.dist-info/METADATA
zillow_api_s-1.0.1.dist-info/WHEEL
zillow_api_s-1.0.1.dist-info/top_level.txt
zillow_api_s-1.0.1.dist-info/RECORD
