Metadata-Version: 2.1
Name: zillow-api-s
Version: 1.0.1
Summary: Real-Time Zillow API
Home-page: https://github.com/Scrapeit-Cloud/zillow-api-python
Author: Roman Milyushkevich
Author-email: roman@scrape-it.cloud
Maintainer: Roman Milyushkevich
Maintainer-email: roman@scrape-it.cloud
License: MIT
Classifier: License :: OSI Approved :: MIT License
Classifier: Programming Language :: Python
Classifier: Programming Language :: Python :: 3
Classifier: Programming Language :: Python :: 3.7
Classifier: Programming Language :: Python :: 3.8
Classifier: Programming Language :: Python :: 3.9
Classifier: Programming Language :: Python :: 3.10
Classifier: Programming Language :: Python :: 3.11
Classifier: Topic :: Software Development :: Libraries :: Python Modules
Requires-Python: >=3.6
License-File: LICENSE
Requires-Dist: requests
